{
  "t": "TeleportingOutTask",
  "D": "KillingSetOfGhostsTask",
  "n": "AttackingWhispererTask",
  "o": "DisturbingOddFigureTask",
  "q": "HandlingPrayersTask",
  "b": "WhispererManager",
  "B": "EnteringRealmTask",
  "k": "WalkingToTheBankTask",
  "g": "DrinkingStaminaPotionTask",
  "z": "RestoringPrayerTask",
  "w": "GameEnum",
  "j": "RechargingTridentTask",
  "v": "DrinkingBrewsTask",
  "s": "TakingLootTask",
  "c": "WhispererManager",
  "a": "WhispererManager",
  "e": "GameEnum2",
  "y": "EatingFoodTask",
  "l": "WalkingToBossTask",
  "r": "MovingOutOfMeleeRangeTask",
  "m": "WithdrawingItemsTask",
  "A": "UsingImbuedHeartTask",
  "x": "DroppingEmptyVialsTask",
  "E": "HidingBehindPillarTask",
  "d": "WhispererManager",
  "C": "WalkingOnGreenOrbsTask",
  "p": "DodgingTentaclesTask",
  "i": "WhispererTaskBase",
  "u": "WhispererTaskBase",
  "f": "WhispererTaskBase"
}