{
  "G": "ReturningToStartTask",
  "t": "DrinkingAntipoisonTask",
  "D": "HealingUpTask",
  "n": "HoppingForAnEmptyWorldTask",
  "o": "LuringNewTargetTask",
  "I": "BankingStallsTask",
  "q": "ReturningToTheBlackjackHouseTask",
  "b": "GameEnum",
  "B": "UpdatingStateTask",
  "i": "DroppingUselessItemsTask",
  "k": "BlackjackingTask",
  "z": "UsingShadowVeilTask",
  "H": "RoguesDenTask",
  "w": "PickingTheLockTask",
  "J": "StealingFromStallTask",
  "j": "OpeningCoinPouchesTask",
  "v": "GoingBackInsideTask",
  "c": "GameEnum2",
  "F": "PickpocketingTheTargetTask",
  "a": "ThievingManager",
  "e": "GameEnum3",
  "y": "HandlingDodgyNecklacesTask",
  "l": "BuyingWinesTask",
  "u": "CleaningInventoryTask",
  "r": "UnnotingForExtraFoodTask",
  "m": "CancellingAttackingBanditthugTask",
  "A": "DoingVyreStuffTask",
  "x": "DepositingSeedsTask",
  "E": "WalkingToBankTask",
  "d": "GameEnum4",
  "f": "GameEnum5",
  "C": "BankingLootFromPickpocketingTask",
  "p": "ThievingManager",
  "K": "WalkingToStallTask",
  "h": "GameEnum6",
  "g": "GHelper",
  "s": "ThievingTaskBase"
}